lol_dto/__init__.py
lol_dto/classes/__init__.py
lol_dto/classes/game/__init__.py
lol_dto/classes/game/lol_game.py
lol_dto/classes/game/lol_game_event.py
lol_dto/classes/game/lol_game_player.py
lol_dto/classes/game/lol_game_team.py
lol_dto/classes/game/position.py
lol_dto/classes/sources/__init__.py
lol_dto/classes/sources/empty_dataclass.py
lol_dto/classes/sources/riot_lol_api.py
lol_dto/names_helper/__init__.py
lol_dto/names_helper/name_classes.py
lol_dto/utilities/__init__.py
lol_dto/utilities/dump_json.py
lol_dto-2.1.0a1.dist-info/LICENSE
lol_dto-2.1.0a1.dist-info/WHEEL
lol_dto-2.1.0a1.dist-info/METADATA
lol_dto-2.1.0a1.dist-info/RECORD
