Metadata-Version: 2.1
Name: lol-dto
Version: 2.1.0a1
Summary: A unified representation of League of Legends-related information
License: MIT
Author: mrtolkien
Author-email: gary.mialaret+pypi@gmail.com
Requires-Python: >=3.8,<4.0
Classifier: License :: OSI Approved :: MIT License
Classifier: Programming Language :: Python :: 3
Classifier: Programming Language :: Python :: 3.10
Classifier: Programming Language :: Python :: 3.8
Classifier: Programming Language :: Python :: 3.9
Provides-Extra: names
Requires-Dist: lol-id-tools (>=2.0.0,<3.0.0); extra == "names"
